cog_worker/__init__.py
cog_worker/distributed.py
cog_worker/manager.py
cog_worker/py.typed
cog_worker/types.py
cog_worker/utils.py
cog_worker/worker.py
cog_worker-0.3.0.dist-info/LICENSE.txt
cog_worker-0.3.0.dist-info/METADATA
cog_worker-0.3.0.dist-info/WHEEL
cog_worker-0.3.0.dist-info/top_level.txt
cog_worker-0.3.0.dist-info/RECORD
