Metadata-Version: 2.1
Name: cog_worker
Version: 0.3.0
Summary: Scalable geospatial analysis on Cloud Optimized GeoTIFFs.
Author-email: Francis Gassert <francis.gassert@vizzuality.com>
License: MIT License
Project-URL: Homepage, https://github.com/vizzuality/cog_worker
Project-URL: Issues, https://github.com/vizzuality/cog_worker/issues
Keywords: cog,geotiff,raster,gdal,rasterio,dask
Classifier: Intended Audience :: Information Technology
Classifier: Intended Audience :: Science/Research
Classifier: License :: OSI Approved :: MIT License
Classifier: Programming Language :: Python :: 3
Classifier: Programming Language :: Python :: 3.8
Classifier: Programming Language :: Python :: 3.9
Classifier: Programming Language :: Python :: 3.10
Classifier: Programming Language :: Python :: 3.11
Classifier: Programming Language :: Python :: 3.12
Classifier: Topic :: Scientific/Engineering :: GIS
Requires-Python: >=3.9
License-File: LICENSE.txt
Requires-Dist: numpy >=1
Requires-Dist: pyproj >=3.0.0
Requires-Dist: rasterio >=1.3
Requires-Dist: morecantile <6.0.0,>=5.0.0
Requires-Dist: rio-tiler <7.0.0,>=6.0.0
Provides-Extra: dev
Requires-Dist: pre-commit ; extra == 'dev'
Requires-Dist: bump-my-version ; extra == 'dev'
Provides-Extra: distributed
Requires-Dist: dask[distributed] ; extra == 'distributed'
Provides-Extra: docs
Requires-Dist: Sphinx ; extra == 'docs'
Requires-Dist: sphinxcontrib-napoleon ; extra == 'docs'
Requires-Dist: furo ; extra == 'docs'
Requires-Dist: nbsphinx ; extra == 'docs'
Requires-Dist: nbconvert ; extra == 'docs'
Provides-Extra: test
Requires-Dist: pytest ; extra == 'test'
